{
  ".svelte-kit/generated/nodes/0.js": {
    "file": "_app/immutable/chunks/0-45bd5b2d.js",
    "imports": [
      "__layout-da46b06b.js",
      "node_modules/@sveltejs/kit/src/runtime/components/layout.svelte"
    ],
    "isDynamicEntry": true,
    "src": ".svelte-kit/generated/nodes/0.js"
  },
  ".svelte-kit/generated/nodes/1.js": {
    "file": "_app/immutable/chunks/1-9014296c.js",
    "imports": [
      "node_modules/@sveltejs/kit/src/runtime/components/error.svelte"
    ],
    "isDynamicEntry": true,
    "src": ".svelte-kit/generated/nodes/1.js"
  },
  ".svelte-kit/generated/nodes/2.js": {
    "file": "_app/immutable/chunks/2-2c4d9021.js",
    "imports": [
      "__layout-fca24c55.js",
      "src/routes/(base)/+layout.svelte"
    ],
    "isDynamicEntry": true,
    "src": ".svelte-kit/generated/nodes/2.js"
  },
  ".svelte-kit/generated/nodes/3.js": {
    "file": "_app/immutable/chunks/3-e4f8a872.js",
    "imports": [
      "__page-469dcf3e.js",
      "src/routes/(base)/+page.svelte"
    ],
    "isDynamicEntry": true,
    "src": ".svelte-kit/generated/nodes/3.js"
  },
  ".svelte-kit/generated/nodes/4.js": {
    "file": "_app/immutable/chunks/4-8a160bfe.js",
    "imports": [
      "__page-79e88579.js",
      "src/routes/(base)/news/+page.svelte"
    ],
    "isDynamicEntry": true,
    "src": ".svelte-kit/generated/nodes/4.js"
  },
  ".svelte-kit/generated/nodes/5.js": {
    "file": "_app/immutable/chunks/5-cbe91ba6.js",
    "imports": [
      "__page-f1fb7eed.js",
      "src/routes/cv/+page.svelte"
    ],
    "isDynamicEntry": true,
    "src": ".svelte-kit/generated/nodes/5.js"
  },
  ".svelte-kit/generated/nodes/6.js": {
    "file": "_app/immutable/chunks/6-32053c04.js",
    "imports": [
      "__page-1822699d.js",
      "src/routes/paper/[slug]/+page.svelte"
    ],
    "isDynamicEntry": true,
    "src": ".svelte-kit/generated/nodes/6.js"
  },
  "Footer.css": {
    "file": "_app/immutable/assets/Footer-6b856700.css",
    "src": "Footer.css"
  },
  "Links.css": {
    "file": "_app/immutable/assets/Links-72cd2b69.css",
    "src": "Links.css"
  },
  "Social.css": {
    "file": "_app/immutable/assets/Social-8d9510f7.css",
    "src": "Social.css"
  },
  "_Footer-c4137f71.js": {
    "css": [
      "_app/immutable/assets/Footer-6b856700.css"
    ],
    "file": "_app/immutable/chunks/Footer-c4137f71.js",
    "imports": [
      "_index-d9827912.js"
    ]
  },
  "_Intro-63471a14.js": {
    "file": "_app/immutable/chunks/Intro-63471a14.js",
    "imports": [
      "_index-d9827912.js"
    ]
  },
  "_Links-ab84c899.js": {
    "css": [
      "_app/immutable/assets/Links-72cd2b69.css"
    ],
    "file": "_app/immutable/chunks/Links-ab84c899.js",
    "imports": [
      "_index-d9827912.js"
    ]
  },
  "_Social-1953bd8f.js": {
    "css": [
      "_app/immutable/assets/Social-8d9510f7.css"
    ],
    "file": "_app/immutable/chunks/Social-1953bd8f.js",
    "imports": [
      "_index-d9827912.js"
    ]
  },
  "__layout-da46b06b.js": {
    "file": "_app/immutable/chunks/_layout-da46b06b.js"
  },
  "__layout-fca24c55.js": {
    "file": "_app/immutable/chunks/_layout-fca24c55.js"
  },
  "__page-1822699d.js": {
    "file": "_app/immutable/chunks/_page-1822699d.js",
    "imports": [
      "_js-yaml-38530ef5.js"
    ]
  },
  "__page-469dcf3e.js": {
    "file": "_app/immutable/chunks/_page-469dcf3e.js",
    "imports": [
      "_js-yaml-38530ef5.js",
      "_publist-7fa7816c.js"
    ]
  },
  "__page-79e88579.js": {
    "file": "_app/immutable/chunks/_page-79e88579.js",
    "imports": [
      "_js-yaml-38530ef5.js"
    ]
  },
  "__page-f1fb7eed.js": {
    "file": "_app/immutable/chunks/_page-f1fb7eed.js",
    "imports": [
      "_publist-7fa7816c.js",
      "_js-yaml-38530ef5.js"
    ]
  },
  "_index-d9827912.js": {
    "file": "_app/immutable/chunks/index-d9827912.js"
  },
  "_js-yaml-38530ef5.js": {
    "file": "_app/immutable/chunks/js-yaml-38530ef5.js"
  },
  "_publist-7fa7816c.js": {
    "file": "_app/immutable/chunks/publist-7fa7816c.js"
  },
  "_singletons-8e0ce3a3.js": {
    "file": "_app/immutable/chunks/singletons-8e0ce3a3.js",
    "imports": [
      "_index-d9827912.js"
    ]
  },
  "node_modules/@sveltejs/kit/src/runtime/client/start.js": {
    "dynamicImports": [
      ".svelte-kit/generated/nodes/0.js",
      ".svelte-kit/generated/nodes/1.js",
      ".svelte-kit/generated/nodes/2.js",
      ".svelte-kit/generated/nodes/3.js",
      ".svelte-kit/generated/nodes/4.js",
      ".svelte-kit/generated/nodes/5.js",
      ".svelte-kit/generated/nodes/6.js"
    ],
    "file": "_app/immutable/start-29accea3.js",
    "imports": [
      "_index-d9827912.js",
      "_singletons-8e0ce3a3.js"
    ],
    "isEntry": true,
    "src": "node_modules/@sveltejs/kit/src/runtime/client/start.js"
  },
  "node_modules/@sveltejs/kit/src/runtime/components/error.svelte": {
    "file": "_app/immutable/components/error.svelte-fb51c1ae.js",
    "imports": [
      "_index-d9827912.js",
      "_singletons-8e0ce3a3.js"
    ],
    "isEntry": true,
    "src": "node_modules/@sveltejs/kit/src/runtime/components/error.svelte"
  },
  "node_modules/@sveltejs/kit/src/runtime/components/layout.svelte": {
    "file": "_app/immutable/components/layout.svelte-22ef87ee.js",
    "imports": [
      "_index-d9827912.js"
    ],
    "isEntry": true,
    "src": "node_modules/@sveltejs/kit/src/runtime/components/layout.svelte"
  },
  "src/routes/(base)/+layout.css": {
    "file": "_app/immutable/assets/_layout-7881511e.css",
    "src": "src/routes/(base)/+layout.css"
  },
  "src/routes/(base)/+layout.js": {
    "file": "_app/immutable/modules/pages/(base)/_layout.js-e992bf42.js",
    "imports": [
      "__layout-fca24c55.js"
    ],
    "isEntry": true,
    "src": "src/routes/(base)/+layout.js"
  },
  "src/routes/(base)/+layout.svelte": {
    "css": [
      "_app/immutable/assets/_layout-7881511e.css"
    ],
    "file": "_app/immutable/components/pages/(base)/_layout.svelte-dc4a0ac5.js",
    "imports": [
      "_index-d9827912.js",
      "_Social-1953bd8f.js",
      "_Footer-c4137f71.js"
    ],
    "isEntry": true,
    "src": "src/routes/(base)/+layout.svelte"
  },
  "src/routes/(base)/+page.css": {
    "file": "_app/immutable/assets/_page-f6eaac6c.css",
    "src": "src/routes/(base)/+page.css"
  },
  "src/routes/(base)/+page.js": {
    "file": "_app/immutable/modules/pages/(base)/_page.js-64ae4f82.js",
    "imports": [
      "_js-yaml-38530ef5.js",
      "_publist-7fa7816c.js",
      "__page-469dcf3e.js"
    ],
    "isEntry": true,
    "src": "src/routes/(base)/+page.js"
  },
  "src/routes/(base)/+page.svelte": {
    "css": [
      "_app/immutable/assets/_page-f6eaac6c.css"
    ],
    "file": "_app/immutable/components/pages/(base)/_page.svelte-c24f6a69.js",
    "imports": [
      "_index-d9827912.js",
      "_Intro-63471a14.js",
      "_Links-ab84c899.js"
    ],
    "isEntry": true,
    "src": "src/routes/(base)/+page.svelte"
  },
  "src/routes/(base)/news/+page.js": {
    "file": "_app/immutable/modules/pages/(base)/news/_page.js-2c5e637f.js",
    "imports": [
      "_js-yaml-38530ef5.js",
      "__page-79e88579.js"
    ],
    "isEntry": true,
    "src": "src/routes/(base)/news/+page.js"
  },
  "src/routes/(base)/news/+page.svelte": {
    "file": "_app/immutable/components/pages/(base)/news/_page.svelte-a7b24438.js",
    "imports": [
      "_index-d9827912.js"
    ],
    "isEntry": true,
    "src": "src/routes/(base)/news/+page.svelte"
  },
  "src/routes/+layout.js": {
    "file": "_app/immutable/modules/pages/_layout.js-9cbb603b.js",
    "imports": [
      "__layout-da46b06b.js"
    ],
    "isEntry": true,
    "src": "src/routes/+layout.js"
  },
  "src/routes/cv/+page.css": {
    "file": "_app/immutable/assets/_page-dcb6fd36.css",
    "src": "src/routes/cv/+page.css"
  },
  "src/routes/cv/+page.js": {
    "file": "_app/immutable/modules/pages/cv/_page.js-62f3a687.js",
    "imports": [
      "_publist-7fa7816c.js",
      "_js-yaml-38530ef5.js",
      "__page-f1fb7eed.js"
    ],
    "isEntry": true,
    "src": "src/routes/cv/+page.js"
  },
  "src/routes/cv/+page.svelte": {
    "css": [
      "_app/immutable/assets/_page-dcb6fd36.css"
    ],
    "file": "_app/immutable/components/pages/cv/_page.svelte-3b828780.js",
    "imports": [
      "_index-d9827912.js",
      "_Intro-63471a14.js",
      "_Links-ab84c899.js",
      "_Social-1953bd8f.js"
    ],
    "isEntry": true,
    "src": "src/routes/cv/+page.svelte"
  },
  "src/routes/paper/[slug]/+page.css": {
    "file": "_app/immutable/assets/_page-31072b5e.css",
    "src": "src/routes/paper/[slug]/+page.css"
  },
  "src/routes/paper/[slug]/+page.js": {
    "file": "_app/immutable/modules/pages/paper/_slug_/_page.js-5fc89f97.js",
    "imports": [
      "_js-yaml-38530ef5.js",
      "__page-1822699d.js"
    ],
    "isEntry": true,
    "src": "src/routes/paper/[slug]/+page.js"
  },
  "src/routes/paper/[slug]/+page.svelte": {
    "css": [
      "_app/immutable/assets/_page-31072b5e.css"
    ],
    "file": "_app/immutable/components/pages/paper/_slug_/_page.svelte-70226c58.js",
    "imports": [
      "_index-d9827912.js",
      "_Footer-c4137f71.js",
      "_Links-ab84c899.js"
    ],
    "isEntry": true,
    "src": "src/routes/paper/[slug]/+page.svelte"
  }
}