{
  "node_modules/@sveltejs/kit/src/runtime/client/start.js": {
    "file": "_app/immutable/start-80aa8661.js",
    "src": "node_modules/@sveltejs/kit/src/runtime/client/start.js",
    "isEntry": true,
    "imports": [
      "_index-0696beeb.js",
      "_singletons-432b7cb4.js"
    ],
    "dynamicImports": [
      ".svelte-kit/generated/nodes/0.js",
      ".svelte-kit/generated/nodes/1.js",
      ".svelte-kit/generated/nodes/2.js",
      ".svelte-kit/generated/nodes/3.js",
      ".svelte-kit/generated/nodes/4.js",
      ".svelte-kit/generated/nodes/5.js",
      ".svelte-kit/generated/nodes/6.js",
      ".svelte-kit/generated/nodes/7.js"
    ]
  },
  "node_modules/@sveltejs/kit/src/runtime/components/layout.svelte": {
    "file": "_app/immutable/components/layout.svelte-09dc7409.js",
    "src": "node_modules/@sveltejs/kit/src/runtime/components/layout.svelte",
    "isEntry": true,
    "imports": [
      "_index-0696beeb.js"
    ]
  },
  "node_modules/@sveltejs/kit/src/runtime/components/error.svelte": {
    "file": "_app/immutable/components/error.svelte-b2f8b560.js",
    "src": "node_modules/@sveltejs/kit/src/runtime/components/error.svelte",
    "isEntry": true,
    "imports": [
      "_index-0696beeb.js",
      "_singletons-432b7cb4.js"
    ]
  },
  "src/routes/(base)/+layout.svelte": {
    "file": "_app/immutable/components/pages/(base)/_layout.svelte-0eab19b8.js",
    "src": "src/routes/(base)/+layout.svelte",
    "isEntry": true,
    "imports": [
      "_index-0696beeb.js",
      "_Social-e41f5cd9.js",
      "_Footer-d186a1f9.js"
    ],
    "css": [
      "_app/immutable/assets/_layout-7881511e.css"
    ]
  },
  "src/routes/cv/+layout.svelte": {
    "file": "_app/immutable/components/pages/cv/_layout.svelte-52b302ac.js",
    "src": "src/routes/cv/+layout.svelte",
    "isEntry": true,
    "imports": [
      "_index-0696beeb.js"
    ]
  },
  "src/routes/(base)/+page.svelte": {
    "file": "_app/immutable/components/pages/(base)/_page.svelte-0362aa7c.js",
    "src": "src/routes/(base)/+page.svelte",
    "isEntry": true,
    "imports": [
      "_index-0696beeb.js",
      "_Intro-eb47d578.js",
      "_Links-a99bb8af.js"
    ],
    "css": [
      "_app/immutable/assets/_page-2e0fe5d1.css"
    ]
  },
  "src/routes/(base)/news/+page.svelte": {
    "file": "_app/immutable/components/pages/(base)/news/_page.svelte-a8208809.js",
    "src": "src/routes/(base)/news/+page.svelte",
    "isEntry": true,
    "imports": [
      "_index-0696beeb.js"
    ]
  },
  "src/routes/cv/+page.svelte": {
    "file": "_app/immutable/components/pages/cv/_page.svelte-92336734.js",
    "src": "src/routes/cv/+page.svelte",
    "isEntry": true,
    "imports": [
      "_index-0696beeb.js",
      "_Intro-eb47d578.js",
      "_Social-e41f5cd9.js",
      "_Links-a99bb8af.js"
    ],
    "css": [
      "_app/immutable/assets/_page-4a9df64c.css"
    ]
  },
  "src/routes/paper/[slug]/+page.svelte": {
    "file": "_app/immutable/components/pages/paper/_slug_/_page.svelte-04d74961.js",
    "src": "src/routes/paper/[slug]/+page.svelte",
    "isEntry": true,
    "imports": [
      "_index-0696beeb.js",
      "_Footer-d186a1f9.js",
      "_Links-a99bb8af.js"
    ],
    "css": [
      "_app/immutable/assets/_page-ae5eb0fe.css"
    ]
  },
  "src/routes/+layout.js": {
    "file": "_app/immutable/modules/pages/_layout.js-7b9cbfbc.js",
    "src": "src/routes/+layout.js",
    "isEntry": true,
    "imports": [
      "__layout-8d2a742b.js"
    ]
  },
  "src/routes/(base)/+layout.js": {
    "file": "_app/immutable/modules/pages/(base)/_layout.js-fa6cc6b6.js",
    "src": "src/routes/(base)/+layout.js",
    "isEntry": true,
    "imports": [
      "__layout-8e88781c.js"
    ]
  },
  "src/routes/(base)/+page.js": {
    "file": "_app/immutable/modules/pages/(base)/_page.js-e8152e3e.js",
    "src": "src/routes/(base)/+page.js",
    "isEntry": true,
    "imports": [
      "_js-yaml-f8efc9bc.js",
      "_publist-2b788674.js",
      "__page-11e2b142.js"
    ]
  },
  "src/routes/(base)/news/+page.js": {
    "file": "_app/immutable/modules/pages/(base)/news/_page.js-db94bbad.js",
    "src": "src/routes/(base)/news/+page.js",
    "isEntry": true,
    "imports": [
      "_js-yaml-f8efc9bc.js",
      "__page-c3891064.js"
    ]
  },
  "src/routes/cv/+page.js": {
    "file": "_app/immutable/modules/pages/cv/_page.js-f7639dac.js",
    "src": "src/routes/cv/+page.js",
    "isEntry": true,
    "imports": [
      "_publist-2b788674.js",
      "_js-yaml-f8efc9bc.js",
      "__page-cd8510d9.js"
    ]
  },
  "src/routes/paper/[slug]/+page.js": {
    "file": "_app/immutable/modules/pages/paper/_slug_/_page.js-491846b6.js",
    "src": "src/routes/paper/[slug]/+page.js",
    "isEntry": true,
    "imports": [
      "_js-yaml-f8efc9bc.js",
      "__page-f2f4d657.js"
    ]
  },
  "_singletons-432b7cb4.js": {
    "file": "_app/immutable/chunks/singletons-432b7cb4.js",
    "imports": [
      "_index-0696beeb.js"
    ]
  },
  "_index-0696beeb.js": {
    "file": "_app/immutable/chunks/index-0696beeb.js"
  },
  "__layout-8d2a742b.js": {
    "file": "_app/immutable/chunks/_layout-8d2a742b.js"
  },
  "_Footer-d186a1f9.js": {
    "file": "_app/immutable/chunks/Footer-d186a1f9.js",
    "imports": [
      "_index-0696beeb.js"
    ],
    "css": [
      "_app/immutable/assets/Footer-6b856700.css"
    ]
  },
  "_Social-e41f5cd9.js": {
    "file": "_app/immutable/chunks/Social-e41f5cd9.js",
    "imports": [
      "_index-0696beeb.js"
    ],
    "css": [
      "_app/immutable/assets/Social-8d9510f7.css"
    ]
  },
  "__layout-8e88781c.js": {
    "file": "_app/immutable/chunks/_layout-8e88781c.js"
  },
  "_Intro-eb47d578.js": {
    "file": "_app/immutable/chunks/Intro-eb47d578.js",
    "imports": [
      "_index-0696beeb.js"
    ],
    "css": [
      "_app/immutable/assets/Intro-3c2639d7.css"
    ]
  },
  "_Links-a99bb8af.js": {
    "file": "_app/immutable/chunks/Links-a99bb8af.js",
    "imports": [
      "_index-0696beeb.js"
    ]
  },
  "__page-11e2b142.js": {
    "file": "_app/immutable/chunks/_page-11e2b142.js",
    "imports": [
      "_js-yaml-f8efc9bc.js",
      "_publist-2b788674.js"
    ]
  },
  "_js-yaml-f8efc9bc.js": {
    "file": "_app/immutable/chunks/js-yaml-f8efc9bc.js"
  },
  "_publist-2b788674.js": {
    "file": "_app/immutable/chunks/publist-2b788674.js"
  },
  "__page-c3891064.js": {
    "file": "_app/immutable/chunks/_page-c3891064.js",
    "imports": [
      "_js-yaml-f8efc9bc.js"
    ]
  },
  "__page-cd8510d9.js": {
    "file": "_app/immutable/chunks/_page-cd8510d9.js",
    "imports": [
      "_publist-2b788674.js",
      "_js-yaml-f8efc9bc.js"
    ]
  },
  "__page-f2f4d657.js": {
    "file": "_app/immutable/chunks/_page-f2f4d657.js",
    "imports": [
      "_js-yaml-f8efc9bc.js"
    ]
  },
  ".svelte-kit/generated/nodes/0.js": {
    "file": "_app/immutable/chunks/0-e6b231eb.js",
    "src": ".svelte-kit/generated/nodes/0.js",
    "isDynamicEntry": true,
    "imports": [
      "__layout-8d2a742b.js",
      "node_modules/@sveltejs/kit/src/runtime/components/layout.svelte"
    ]
  },
  ".svelte-kit/generated/nodes/1.js": {
    "file": "_app/immutable/chunks/1-12b35af0.js",
    "src": ".svelte-kit/generated/nodes/1.js",
    "isDynamicEntry": true,
    "imports": [
      "node_modules/@sveltejs/kit/src/runtime/components/error.svelte"
    ]
  },
  ".svelte-kit/generated/nodes/2.js": {
    "file": "_app/immutable/chunks/2-411b0863.js",
    "src": ".svelte-kit/generated/nodes/2.js",
    "isDynamicEntry": true,
    "imports": [
      "__layout-8e88781c.js",
      "src/routes/(base)/+layout.svelte"
    ]
  },
  ".svelte-kit/generated/nodes/3.js": {
    "file": "_app/immutable/chunks/3-e15b41d7.js",
    "src": ".svelte-kit/generated/nodes/3.js",
    "isDynamicEntry": true,
    "imports": [
      "src/routes/cv/+layout.svelte"
    ]
  },
  ".svelte-kit/generated/nodes/4.js": {
    "file": "_app/immutable/chunks/4-36313735.js",
    "src": ".svelte-kit/generated/nodes/4.js",
    "isDynamicEntry": true,
    "imports": [
      "__page-11e2b142.js",
      "src/routes/(base)/+page.svelte"
    ]
  },
  ".svelte-kit/generated/nodes/5.js": {
    "file": "_app/immutable/chunks/5-faa3383a.js",
    "src": ".svelte-kit/generated/nodes/5.js",
    "isDynamicEntry": true,
    "imports": [
      "__page-c3891064.js",
      "src/routes/(base)/news/+page.svelte"
    ]
  },
  ".svelte-kit/generated/nodes/6.js": {
    "file": "_app/immutable/chunks/6-3e49cae9.js",
    "src": ".svelte-kit/generated/nodes/6.js",
    "isDynamicEntry": true,
    "imports": [
      "__page-cd8510d9.js",
      "src/routes/cv/+page.svelte"
    ]
  },
  ".svelte-kit/generated/nodes/7.js": {
    "file": "_app/immutable/chunks/7-f528006e.js",
    "src": ".svelte-kit/generated/nodes/7.js",
    "isDynamicEntry": true,
    "imports": [
      "__page-f2f4d657.js",
      "src/routes/paper/[slug]/+page.svelte"
    ]
  },
  "src/routes/(base)/+layout.css": {
    "file": "_app/immutable/assets/_layout-7881511e.css",
    "src": "src/routes/(base)/+layout.css"
  },
  "Footer.css": {
    "file": "_app/immutable/assets/Footer-6b856700.css",
    "src": "Footer.css"
  },
  "Social.css": {
    "file": "_app/immutable/assets/Social-8d9510f7.css",
    "src": "Social.css"
  },
  "Intro.css": {
    "file": "_app/immutable/assets/Intro-3c2639d7.css",
    "src": "Intro.css"
  },
  "src/routes/cv/+page.css": {
    "file": "_app/immutable/assets/_page-4a9df64c.css",
    "src": "src/routes/cv/+page.css"
  },
  "src/routes/(base)/+page.css": {
    "file": "_app/immutable/assets/_page-2e0fe5d1.css",
    "src": "src/routes/(base)/+page.css"
  },
  "src/routes/paper/[slug]/+page.css": {
    "file": "_app/immutable/assets/_page-ae5eb0fe.css",
    "src": "src/routes/paper/[slug]/+page.css"
  }
}